rex/__init__.py
rex/cryptography.py
rex/interface.py
rex/models.py
rex_password_manager-3.7.9.dist-info/METADATA
rex_password_manager-3.7.9.dist-info/WHEEL
rex_password_manager-3.7.9.dist-info/entry_points.txt
rex_password_manager-3.7.9.dist-info/licenses/LICENSE
rex_password_manager-3.7.9.dist-info/RECORD
