Metadata-Version: 2.3
Name: rex-password-manager
Version: 3.7.9
Summary: A powerful terminal password manager using AES encryption and python
Project-URL: Homepage, https://github.com/Cromizone/rex
Project-URL: Issues, https://github.com/Cromizone/rex/issues
Author-email: Nithin <cromizonebolt@gmail.com>
License: MIT License
License-File: LICENSE
Keywords: AES encryption,passphrase,password,password manager,python,terminal,typer
Classifier: License :: OSI Approved :: MIT License
Classifier: Operating System :: OS Independent
Classifier: Programming Language :: Python :: 3
Requires-Python: >=3.0
Requires-Dist: bcrypt==4.0.1
Requires-Dist: pycryptodome==3.20.0
Requires-Dist: pydantic==2.5.3
Requires-Dist: pyperclip==1.8.2
Requires-Dist: rich==13.7.0
Requires-Dist: typer==0.9.0
